ejercicios/ej4/registro_orden.sv
// Guarda índices, no contenidos del banco.
module registro_orden (
    input logic clk, rst, capture_en,
    input logic [4:0] rs1, rs2, rd,
    input logic [2:0] opcode,
    output logic [4:0] rs1_q, rs2_q, rd_q,
    output logic [2:0] op_q
);
    always_ff @(posedge clk or posedge rst) begin
        if (rst) begin
            rs1_q <= '0;
            rs2_q <= '0;
            rd_q <= '0;
            op_q <= '0;
        end else if (capture_en) begin
            // COMPLETAR: guardar la orden.
            rs1_q <= rs1;
            rs2_q <= rs2;
            rd_q <= rd;
            op_q <= opcode;
        end
    end
endmodule

ejercicios/ej4/registro_orden_tb.sv
`timescale 1ns/1ps
module registro_orden_tb;
    logic clk = 0;
    always #5 clk = ~clk;
    task automatic tick();
        @(posedge clk); #1;
    endtask
    initial begin
        #10000;
        $fatal(1, "TIMEOUT: la simulación no terminó");
    end
    logic rst=1, capture_en=0;
    logic [4:0] rs1=0,rs2=0,rd=0,rs1_q,rs2_q,rd_q;
    logic [2:0] opcode=0,op_q;
    registro_orden dut (.*);
    task automatic check(input logic [4:0] a,b,d, input logic [2:0] op);
        if ({rs1_q,rs2_q,rd_q,op_q} !== {a,b,d,op}) $fatal(1, "Orden capturada incorrecta");
    endtask
    initial begin
        $dumpfile("sim.vcd"); $dumpvars;
        tick(); check(0,0,0,0);
        @(negedge clk); rst=0; rs1=1; rs2=2; rd=5; opcode=1;
        tick(); check(0,0,0,0);
        @(negedge clk); capture_en=1; #1; check(0,0,0,0);
        tick(); check(1,2,5,1);
        @(negedge clk); capture_en=0; rs1=8; rs2=9; rd=10; opcode=7;
        repeat(2) begin tick(); check(1,2,5,1); end
        @(negedge clk); capture_en=1;
        tick(); check(8,9,10,7);
        @(negedge clk); rst=1; #1; check(0,0,0,0);
        $display("PASS ej4: captura, retención y reset asíncrono"); $finish;
    end

endmodule

ejercicios/ej4/obj_dir/sim.vcd
$version Generated by VerilatedVcd $end
$timescale 1ps $end
 $scope module registro_orden_tb $end
  $var wire 1 & clk $end
  $var wire 1 ' rst $end
  $var wire 1 ( capture_en $end
  $var wire 5 ) rs1 [4:0] $end
  $var wire 5 * rs2 [4:0] $end
  $var wire 5 + rd [4:0] $end
  $var wire 5 " rs1_q [4:0] $end
  $var wire 5 # rs2_q [4:0] $end
  $var wire 5 $ rd_q [4:0] $end
  $var wire 3 , opcode [2:0] $end
  $var wire 3 % op_q [2:0] $end
  $scope module dut $end
   $var wire 1 & clk $end
   $var wire 1 ' rst $end
   $var wire 1 ( capture_en $end
   $var wire 5 ) rs1 [4:0] $end
   $var wire 5 * rs2 [4:0] $end
   $var wire 5 + rd [4:0] $end
   $var wire 3 , opcode [2:0] $end
   $var wire 5 " rs1_q [4:0] $end
   $var wire 5 # rs2_q [4:0] $end
   $var wire 5 $ rd_q [4:0] $end
   $var wire 3 % op_q [2:0] $end
  $upscope $end
 $upscope $end
$enddefinitions $end


#0
b00000 "
b00000 #
b00000 $
b000 %
0&
1'
0(
b00000 )
b00000 *
b00000 +
b000 ,
#5000
1&
#10000
0&
0'
b00001 )
b00010 *
b00101 +
b001 ,
#15000
1&
#20000
0&
1(
#25000
b00001 "
b00010 #
b00101 $
b001 %
1&
#30000
0&
0(
b01000 )
b01001 *
b01010 +
b111 ,
#35000
1&
#40000
0&
#45000
1&
#50000
0&
1(
#55000
b01000 "
b01001 #
b01010 $
b111 %
1&
#60000
b00000 "
b00000 #
b00000 $
b000 %
0&
1'
